python_supporter/__init__.py
python_supporter/cache.py
python_supporter/check_ip.py
python_supporter/config.py
python_supporter/file.py
python_supporter/logging.py
python_supporter/random.py
python_supporter/socket.py
python_supporter-0.0.19.dist-info/METADATA
python_supporter-0.0.19.dist-info/WHEEL
python_supporter-0.0.19.dist-info/top_level.txt
python_supporter-0.0.19.dist-info/RECORD
