Metadata-Version: 2.1
Name: python-supporter
Version: 0.0.19
Summary: Python supporter
Home-page: https://github.com/automatethem/python-supporter
Author: Sang Ki Kwon
Author-email: automatethem@gmail.com
License: MIT
